dsa/__init__.py
dsa/graph.py
dsa/recursion.py
dsa/searching.py
dsa/sorting.py
dsa/utils.py
dsa/algorithms/__init__.py
dsa/algorithms/divide_and_conquer.py
dsa/algorithms/dynamic_programming.py
dsa/algorithms/greedy.py
dsa/structures/__init__.py
dsa/structures/linked_list.py
dsa/structures/queue.py
dsa/structures/stack.py
dsa/structures/tree.py
dsa_toolkit-1.0.1.dist-info/licenses/LICENSE
dsa_toolkit-1.0.1.dist-info/METADATA
dsa_toolkit-1.0.1.dist-info/WHEEL
dsa_toolkit-1.0.1.dist-info/top_level.txt
dsa_toolkit-1.0.1.dist-info/RECORD
