Metadata-Version: 2.4
Name: dsa-toolkit
Version: 1.0.1
Summary: A comprehensive toolkit for Data Structures and Algorithms
Home-page: https://github.com/masoomverma/dsa-toolkit
Author: Masoom Verma
Author-email: Masoom Verma <0xmasoom@gmail.com>
License: MIT
Project-URL: Homepage, https://github.com/masoomverma/dsa-toolkit
Project-URL: Documentation, https://github.com/masoomverma/dsa-toolkit#readme
Project-URL: Repository, https://github.com/masoomverma/dsa-toolkit
Project-URL: Bug Reports, https://github.com/masoomverma/dsa-toolkit/issues
Keywords: data-structures,algorithms,dsa,sorting,searching,graphs,trees
Classifier: Development Status :: 4 - Beta
Classifier: Intended Audience :: Education
Classifier: Intended Audience :: Developers
Classifier: Topic :: Education
Classifier: Topic :: Software Development :: Libraries :: Python Modules
Classifier: License :: OSI Approved :: MIT License
Classifier: Programming Language :: Python :: 3
Classifier: Programming Language :: Python :: 3.7
Classifier: Programming Language :: Python :: 3.8
Classifier: Programming Language :: Python :: 3.9
Classifier: Programming Language :: Python :: 3.10
Classifier: Programming Language :: Python :: 3.11
Classifier: Programming Language :: Python :: 3.12
Classifier: Programming Language :: Python :: 3.13
Requires-Python: >=3.7
License-File: LICENSE
Dynamic: author
Dynamic: home-page
Dynamic: license-file
Dynamic: requires-python
